{
  "id": "report_1766246696724",
  "conversationId": "conv_1766246683744",
  "userId": "sato",
  "userName": "佐藤花子",
  "date": "2025-12-20",
  "content": "# 日報 - 佐藤花子 - 2025/12/21\n\n## 本日の業務内容\n- 個別相談・商談の件数: 5件\n- 成約できた案件: 2件\n- 成約できなかった案件: 3件\n  - 成約案件の詳細: クライアントXとの契約成立\n  - 非成約案件の詳細: クライアントYとZが条件面で折り合わず\n\n## 成果・進捗\n- 2件の成約を達成し、目標の50%をクリア\n- 商談の中で顧客ニーズを的確に把握できた\n\n## 課題・困りごと\n- 成約できなかった案件の多くが予算の問題で、クライアントとの距離感を感じる\n- コミュニケーションのタイミングに改善の余地がある\n\n## 明日の予定\n- 他チームとの連携を強化するため、ミーティングを設定\n- 成約できなかったクライアントYに再提案を考える\n\n## 組織への提案・要望\n- 成約に至らなかった案件に関するフィードバックをチームで共有し、次回に活かすための分析を行う提案\n- 予算面の調整を支援するための新たな施策を検討してほしい\n\n## その他メモ\n- クライアントからのフィードバックを活用して、提案内容をブラッシュアップしたい\n\n---\n*この日報は1on1の会話内容からAIが自動生成しました。*",
  "tasks": [],
  "achievements": [],
  "issues": [],
  "tomorrowPlan": [],
  "suggestions": [],
  "createdAt": "2025-12-20T16:04:56.724Z"
}