{
  "id": "report_tanaka_1",
  "conversationId": "conv_tanaka_1",
  "userId": "tanaka",
  "userName": "田中美咲",
  "date": "2024-12-17",
  "content": "# 日報 - 田中美咲 - 2024年12月17日\n\n## 本日の商談結果\n- 個別相談: 4件実施\n- 成約: 2件（成約率50%）\n\n## 成果・良かった点\n- お客様の悩みに寄り添って話を聞けた\n- 2件成約できた\n\n## 課題・困りごと\n- マンネリ化してきてモチベーションが上がらない\n- 入社1年半で成果は出せているが、このまま続けていいか不安\n- キャリアパスが見えない（トップセールス or マネジメント）\n- 将来の道筋が不明確\n\n## 組織への提案・要望\n- 評価制度をもっと明確にしてほしい\n- 昇給条件やリーダー昇格の基準を明示してほしい\n- 成績（数字）だけでなく、新人フォローやチーム貢献も評価してほしい\n\n## 明日の予定\n- 5件で3件成約を目指す\n- 新しいクロージングアプローチを試す\n\n---\n*この日報は1on1の会話内容からAIが自動生成しました。*",
  "tasks": ["個別相談4件実施"],
  "achievements": ["成約率50%", "顧客の悩みに寄り添えた"],
  "issues": ["モチベーション低下", "キャリアパス不明確", "評価制度への不満"],
  "tomorrowPlan": ["5件で3件成約", "新しいアプローチを試す"],
  "suggestions": ["評価制度の明確化", "キャリアパスの可視化", "チーム貢献の評価"],
  "createdAt": "2024-12-17T18:10:00.000Z"
}
